{
  "annotations": {
    "list": []
  },
  "editable": true,
  "gnetId": null,
  "graphTooltip": 0,
  "id": null,
  "links": [],
  "panels": [
    {
      "datasource": "Prometheus",
      "fieldConfig": {
        "defaults": {
          "color": {
            "mode": "thresholds"
          },
          "mappings": [],
          "thresholds": {
            "mode": "absolute",
            "steps": [
              {
                "color": "green",
                "value": null
              }
            ]
          },
          "unit": "short"
        }
      },
      "gridPos": {
        "h": 6,
        "w": 8,
        "x": 0,
        "y": 0
      },
      "id": 1,
      "options": {
        "colorMode": "value",
        "graphMode": "area",
        "justifyMode": "auto",
        "orientation": "auto",
        "reduceOptions": {
          "values": false,
          "calcs": ["lastNotNull"],
          "fields": ""
        },
        "textMode": "auto"
      },
      "targets": [
        {
          "expr": "sonoro_registered_users_total",
          "refId": "A"
        }
      ],
      "title": "Total Registered Users",
      "type": "stat"
    },
    {
      "datasource": "Prometheus",
      "fieldConfig": {
        "defaults": {
          "color": {
            "mode": "thresholds"
          },
          "mappings": [],
          "thresholds": {
            "mode": "absolute",
            "steps": [
              {
                "color": "green",
                "value": null
              }
            ]
          },
          "unit": "short"
        }
      },
      "gridPos": {
        "h": 6,
        "w": 8,
        "x": 8,
        "y": 0
      },
      "id": 2,
      "options": {
        "colorMode": "value",
        "graphMode": "area",
        "justifyMode": "auto",
        "orientation": "auto",
        "reduceOptions": {
          "values": false,
          "calcs": ["lastNotNull"],
          "fields": ""
        },
        "textMode": "auto"
      },
      "targets": [
        {
          "expr": "sonoro_active_users_total",
          "refId": "A"
        }
      ],
      "title": "Active Users (30d)",
      "type": "stat"
    },
    {
      "datasource": "Prometheus",
      "fieldConfig": {
        "defaults": {
          "color": {
            "mode": "thresholds"
          },
          "mappings": [],
          "thresholds": {
            "mode": "absolute",
            "steps": [
              {
                "color": "green",
                "value": null
              },
              {
                "color": "yellow",
                "value": 10
              },
              {
                "color": "red",
                "value": 50
              }
            ]
          },
          "unit": "short"
        }
      },
      "gridPos": {
        "h": 6,
        "w": 8,
        "x": 16,
        "y": 0
      },
      "id": 3,
      "options": {
        "colorMode": "value",
        "graphMode": "area",
        "justifyMode": "auto",
        "orientation": "auto",
        "reduceOptions": {
          "values": false,
          "calcs": ["lastNotNull"],
          "fields": ""
        },
        "textMode": "auto"
      },
      "targets": [
        {
          "expr": "rate(sonoro_auth_login_failures_total[1m]) * 60",
          "refId": "A"
        }
      ],
      "title": "Login Failures (per minute)",
      "type": "stat"
    },
    {
      "datasource": "Prometheus",
      "fieldConfig": {
        "defaults": {
          "color": {
            "mode": "palette-classic"
          },
          "custom": {
            "axisLabel": "",
            "axisPlacement": "auto",
            "barAlignment": 0,
            "drawStyle": "line",
            "fillOpacity": 10,
            "gradientMode": "none",
            "lineInterpolation": "linear",
            "lineWidth": 1,
            "pointSize": 5,
            "showPoints": "never",
            "spanNulls": true
          },
          "mappings": [],
          "thresholds": {
            "mode": "absolute",
            "steps": [
              {
                "color": "green",
                "value": null
              }
            ]
          },
          "unit": "short"
        }
      },
      "gridPos": {
        "h": 8,
        "w": 12,
        "x": 0,
        "y": 6
      },
      "id": 4,
      "options": {
        "legend": {
          "calcs": ["sum"],
          "displayMode": "table",
          "placement": "bottom"
        },
        "tooltip": {
          "mode": "multi"
        }
      },
      "targets": [
        {
          "expr": "rate(sonoro_auth_login_attempts_total{status=\"success\"}[5m]) * 60",
          "legendFormat": "Successful Logins",
          "refId": "A"
        },
        {
          "expr": "rate(sonoro_auth_login_attempts_total{status=\"failure\"}[5m]) * 60",
          "legendFormat": "Failed Logins",
          "refId": "B"
        }
      ],
      "title": "Login Attempts (per minute)",
      "type": "timeseries"
    },
    {
      "datasource": "Prometheus",
      "fieldConfig": {
        "defaults": {
          "color": {
            "mode": "palette-classic"
          },
          "custom": {
            "axisLabel": "",
            "axisPlacement": "auto",
            "barAlignment": 0,
            "drawStyle": "line",
            "fillOpacity": 10,
            "gradientMode": "none",
            "lineInterpolation": "linear",
            "lineWidth": 1,
            "pointSize": 5,
            "showPoints": "never",
            "spanNulls": true
          },
          "mappings": [],
          "thresholds": {
            "mode": "absolute",
            "steps": [
              {
                "color": "green",
                "value": null
              }
            ]
          },
          "unit": "short"
        }
      },
      "gridPos": {
        "h": 8,
        "w": 12,
        "x": 12,
        "y": 6
      },
      "id": 5,
      "options": {
        "legend": {
          "calcs": ["sum"],
          "displayMode": "table",
          "placement": "bottom"
        },
        "tooltip": {
          "mode": "multi"
        }
      },
      "targets": [
        {
          "expr": "sum by(reason) (rate(sonoro_auth_login_failures_total[5m]))",
          "legendFormat": "{{reason}}",
          "refId": "A"
        }
      ],
      "title": "Login Failures by Reason",
      "type": "timeseries"
    },
    {
      "datasource": "Prometheus",
      "fieldConfig": {
        "defaults": {
          "color": {
            "mode": "palette-classic"
          },
          "custom": {
            "axisLabel": "",
            "axisPlacement": "auto",
            "barAlignment": 0,
            "drawStyle": "line",
            "fillOpacity": 10,
            "gradientMode": "none",
            "lineInterpolation": "linear",
            "lineWidth": 1,
            "pointSize": 5,
            "showPoints": "never",
            "spanNulls": true
          },
          "mappings": [],
          "thresholds": {
            "mode": "absolute",
            "steps": [
              {
                "color": "green",
                "value": null
              }
            ]
          },
          "unit": "short"
        }
      },
      "gridPos": {
        "h": 8,
        "w": 12,
        "x": 0,
        "y": 14
      },
      "id": 6,
      "options": {
        "legend": {
          "calcs": ["sum"],
          "displayMode": "table",
          "placement": "bottom"
        },
        "tooltip": {
          "mode": "multi"
        }
      },
      "targets": [
        {
          "expr": "rate(sonoro_auth_registrations_total{status=\"success\"}[5m]) * 60",
          "legendFormat": "Successful Registrations",
          "refId": "A"
        },
        {
          "expr": "rate(sonoro_auth_registrations_total{status=\"failure\"}[5m]) * 60",
          "legendFormat": "Failed Registrations",
          "refId": "B"
        }
      ],
      "title": "User Registrations (per minute)",
      "type": "timeseries"
    },
    {
      "datasource": "Prometheus",
      "fieldConfig": {
        "defaults": {
          "color": {
            "mode": "palette-classic"
          },
          "custom": {
            "axisLabel": "",
            "axisPlacement": "auto",
            "barAlignment": 0,
            "drawStyle": "line",
            "fillOpacity": 10,
            "gradientMode": "none",
            "lineInterpolation": "linear",
            "lineWidth": 1,
            "pointSize": 5,
            "showPoints": "never",
            "spanNulls": true
          },
          "mappings": [],
          "thresholds": {
            "mode": "absolute",
            "steps": [
              {
                "color": "green",
                "value": null
              }
            ]
          },
          "unit": "short"
        }
      },
      "gridPos": {
        "h": 8,
        "w": 12,
        "x": 12,
        "y": 14
      },
      "id": 7,
      "options": {
        "legend": {
          "calcs": ["sum"],
          "displayMode": "table",
          "placement": "bottom"
        },
        "tooltip": {
          "mode": "multi"
        }
      },
      "targets": [
        {
          "expr": "rate(sonoro_auth_token_refreshes_total{status=\"success\"}[5m]) * 60",
          "legendFormat": "Successful Refreshes",
          "refId": "A"
        },
        {
          "expr": "rate(sonoro_auth_token_refreshes_total{status=\"failure\"}[5m]) * 60",
          "legendFormat": "Failed Refreshes",
          "refId": "B"
        }
      ],
      "title": "Token Refreshes (per minute)",
      "type": "timeseries"
    }
  ],
  "schemaVersion": 27,
  "style": "dark",
  "tags": ["sonoro", "authentication", "security"],
  "templating": {
    "list": []
  },
  "time": {
    "from": "now-1h",
    "to": "now"
  },
  "timepicker": {},
  "timezone": "",
  "title": "Sonoro - Authentication",
  "uid": "sonoro-authentication",
  "version": 1
}
